pysisense/__init__.py
pysisense/client.py
pysisense-0.4.dist-info/METADATA
pysisense-0.4.dist-info/WHEEL
pysisense-0.4.dist-info/top_level.txt
pysisense-0.4.dist-info/RECORD
