Metadata-Version: 2.1
Name: pysisense
Version: 0.4
Summary: A Python SDK for interacting with Sisense API
Home-page: https://github.com/hnegi01/pysisense.git
Author: Himanshu Negi
Author-email: himanshu.negi.08@gmail.com
Classifier: Programming Language :: Python :: 3
Classifier: License :: OSI Approved :: MIT License
Classifier: Operating System :: OS Independent
Requires-Python: >=3.6
Requires-Dist: requests
Requires-Dist: pyyaml
Requires-Dist: pandas
